{"dependencies":[{"name":"/Users/tetty/Desktop/programming/Vue/vue_standard/vue_standard/.babelrc","includedInParent":true,"mtime":1529127695000},{"name":"/Users/tetty/Desktop/programming/Vue/vue_standard/vue_standard/package.json","includedInParent":true,"mtime":1529148115000},{"name":"vue/dist/vue.esm.js","loc":{"line":1,"column":16}},{"name":"./lib/lodash.js","loc":{"line":2,"column":14}},{"name":"./vue/App.vue","loc":{"line":3,"column":18}},{"name":"./vue/Ch3.vue","loc":{"line":4,"column":16}},{"name":"./vue/Ch4.vue","loc":{"line":5,"column":16}},{"name":"./vue/Ch5.vue","loc":{"line":6,"column":16}},{"name":"./vue/Ch6.vue","loc":{"line":7,"column":16}}],"generated":{"js":"\"use strict\";var e=require(\"vue/dist/vue.esm.js\"),u=q(e),r=require(\"./lib/lodash.js\"),t=q(r),o=require(\"./vue/App.vue\"),l=q(o),n=require(\"./vue/Ch3.vue\"),a=q(n),v=require(\"./vue/Ch4.vue\"),i=q(v),p=require(\"./vue/Ch5.vue\"),s=q(p),d=require(\"./vue/Ch6.vue\"),m=q(d);function q(e){return e&&e.__esModule?e:{default:e}}u.default.component(\"global-component\",{template:\"<p>{{ globalComponentText }}</p>\",data:function(){return{globalComponentText:\"Hello Vue.js!\"}}});var f=new u.default(m.default);f.$mount(\"#app\");","map":{"mappings":[{"generated":{"line":3,"column":0},"source":"src/app.js","original":{"line":1,"column":0}},{"generated":{"line":7,"column":0},"source":"src/app.js","original":{"line":2,"column":0}},{"generated":{"line":11,"column":0},"source":"src/app.js","original":{"line":3,"column":0}},{"generated":{"line":15,"column":0},"source":"src/app.js","original":{"line":4,"column":0}},{"generated":{"line":19,"column":0},"source":"src/app.js","original":{"line":5,"column":0}},{"generated":{"line":23,"column":0},"source":"src/app.js","original":{"line":6,"column":0}},{"generated":{"line":27,"column":0},"source":"src/app.js","original":{"line":7,"column":0}},{"generated":{"line":33,"column":0},"source":"src/app.js","original":{"line":9,"column":0}},{"name":"Vue","generated":{"line":34,"column":0},"source":"src/app.js","original":{"line":10,"column":0}},{"name":"component","generated":{"line":34,"column":17},"source":"src/app.js","original":{"line":10,"column":4}},{"generated":{"line":34,"column":26},"source":"src/app.js","original":{"line":10,"column":0}},{"generated":{"line":34,"column":27},"source":"src/app.js","original":{"line":10,"column":14}},{"generated":{"line":34,"column":45},"source":"src/app.js","original":{"line":10,"column":0}},{"generated":{"line":34,"column":47},"source":"src/app.js","original":{"line":10,"column":34}},{"name":"template","generated":{"line":35,"column":0},"source":"src/app.js","original":{"line":11,"column":4}},{"generated":{"line":35,"column":14},"source":"src/app.js","original":{"line":11,"column":14}},{"generated":{"line":35,"column":48},"source":"src/app.js","original":{"line":10,"column":34}},{"name":"data","generated":{"line":36,"column":0},"source":"src/app.js","original":{"line":12,"column":4}},{"generated":{"line":36,"column":10},"source":"src/app.js","original":{"line":12,"column":10}},{"generated":{"line":36,"column":26},"source":"src/app.js","original":{"line":12,"column":16}},{"generated":{"line":37,"column":0},"source":"src/app.js","original":{"line":13,"column":8}},{"generated":{"line":37,"column":15},"source":"src/app.js","original":{"line":13,"column":15}},{"name":"globalComponentText","generated":{"line":38,"column":0},"source":"src/app.js","original":{"line":14,"column":12}},{"generated":{"line":38,"column":33},"source":"src/app.js","original":{"line":14,"column":33}},{"generated":{"line":39,"column":0},"source":"src/app.js","original":{"line":13,"column":15}},{"generated":{"line":39,"column":9},"source":"src/app.js","original":{"line":13,"column":8}},{"generated":{"line":40,"column":0},"source":"src/app.js","original":{"line":16,"column":5}},{"generated":{"line":41,"column":0},"source":"src/app.js","original":{"line":10,"column":34}},{"generated":{"line":41,"column":1},"source":"src/app.js","original":{"line":10,"column":0}},{"generated":{"line":43,"column":0},"source":"src/app.js","original":{"line":19,"column":0}},{"name":"app","generated":{"line":43,"column":4},"source":"src/app.js","original":{"line":19,"column":6}},{"generated":{"line":43,"column":10},"source":"src/app.js","original":{"line":19,"column":12}},{"name":"Vue","generated":{"line":43,"column":14},"source":"src/app.js","original":{"line":19,"column":16}},{"generated":{"line":43,"column":30},"source":"src/app.js","original":{"line":19,"column":12}},{"name":"Ch6","generated":{"line":43,"column":31},"source":"src/app.js","original":{"line":19,"column":20}},{"generated":{"line":43,"column":43},"source":"src/app.js","original":{"line":19,"column":12}},{"generated":{"line":43,"column":44},"source":"src/app.js","original":{"line":19,"column":0}},{"name":"app","generated":{"line":44,"column":0},"source":"src/app.js","original":{"line":20,"column":0}},{"name":"$mount","generated":{"line":44,"column":4},"source":"src/app.js","original":{"line":20,"column":4}},{"generated":{"line":44,"column":10},"source":"src/app.js","original":{"line":20,"column":0}},{"generated":{"line":44,"column":11},"source":"src/app.js","original":{"line":20,"column":11}},{"generated":{"line":44,"column":17},"source":"src/app.js","original":{"line":20,"column":0}}],"sources":{"src/app.js":"import Vue from 'vue/dist/vue.esm.js';\nimport _ from './lib/lodash.js';\nimport Hello from './vue/App.vue';\nimport Ch3 from './vue/Ch3.vue';\nimport Ch4 from './vue/Ch4.vue';\nimport Ch5 from './vue/Ch5.vue';\nimport Ch6 from './vue/Ch6.vue';\n\n// this component is root component for Ch5\nVue.component('global-component', {\n    template: '<p>{{ globalComponentText }}</p>',\n    data: () => {\n        return {\n            globalComponentText: 'Hello Vue.js!'\n        }\n    },\n});\n\nconst app = new Vue(Ch6);\napp.$mount('#app');"},"lineCount":null}},"hash":"e856b486cb3f1b532c479fdc06cada2c","cacheData":{"env":{}}}